tap_freshworkscrm/__init__.py
tap_freshworkscrm/tap_utils.py
tap_freshworkscrm/schemas/accounts.json
tap_freshworkscrm/schemas/appointments.json
tap_freshworkscrm/schemas/contacts.json
tap_freshworkscrm/schemas/deals.json
tap_freshworkscrm/schemas/leads.json
tap_freshworkscrm/schemas/owners.json
tap_freshworkscrm/schemas/sales_activities.json
tap_freshworkscrm/schemas/tasks.json
tap_freshworkscrm-0.1.0.dist-info/LICENSE
tap_freshworkscrm-0.1.0.dist-info/METADATA
tap_freshworkscrm-0.1.0.dist-info/WHEEL
tap_freshworkscrm-0.1.0.dist-info/entry_points.txt
tap_freshworkscrm-0.1.0.dist-info/top_level.txt
tap_freshworkscrm-0.1.0.dist-info/RECORD
