Metadata-Version: 2.1
Name: tap-freshworkscrm
Version: 0.1.0
Summary: Singer.io tap for extracting FreshWorks CRM Data
Home-page: http://singer.io
Author: Akilesh Vishwanth
Author-email: akilesh.v@elevate.so
License: UNKNOWN
Platform: UNKNOWN
Classifier: Programming Language :: Python :: 3 :: Only
License-File: LICENSE
Requires-Dist: backoff (==1.8.0)
Requires-Dist: requests (==2.26.0)
Requires-Dist: singer-python (==5.8.1)
Provides-Extra: dev
Requires-Dist: ipdb (==0.11) ; extra == 'dev'
